aioacm/__init__.py
aioacm/client.py
aioacm/command.py
aioacm/commons.py
aioacm/files.py
aioacm/params.py
aioacm/server.py
aioacm_sdk_python-0.3.13.dist-info/LICENSE
aioacm_sdk_python-0.3.13.dist-info/WHEEL
aioacm_sdk_python-0.3.13.dist-info/METADATA
aioacm_sdk_python-0.3.13.dist-info/RECORD
