Metadata-Version: 2.1
Name: aioacm-sdk-python
Version: 0.3.13
Summary: Python client for ACM with asyncio support.
Home-page: https://github.com/ioimop/aioacm
License: Apache-2.0
Author: songww
Author-email: sww4718168@gmail.com
Requires-Python: >=3.5
Classifier: License :: OSI Approved :: Apache Software License
Classifier: Programming Language :: Python :: 3
Classifier: Programming Language :: Python :: 3.5
Classifier: Programming Language :: Python :: 3.6
Classifier: Programming Language :: Python :: 3.7
Requires-Dist: aiohttp (>=3.3,<4.0)
Requires-Dist: aliyun-python-sdk-core-v3 (>=2.8,<3.0)
Requires-Dist: aliyun-python-sdk-kms (>=2.5,<3.0)
